README.md
setup.cfg
setup.py
invest_tracker/AssetClass.py
invest_tracker/__init__.py
invest_traker.egg-info/PKG-INFO
invest_traker.egg-info/SOURCES.txt
invest_traker.egg-info/dependency_links.txt
invest_traker.egg-info/not-zip-safe
invest_traker.egg-info/requires.txt
invest_traker.egg-info/top_level.txt