Metadata-Version: 2.1
Name: invest-traker
Version: 0.1
Summary: Helps to track and manage investments
Home-page: https://github.com/leofmr/invest_tracker
Author: Leonardo Rocha
Author-email: leonardo@moutinho.com.br
License: UNKNOWN
Platform: UNKNOWN
